syringe_pumps/camera_control/XsCamera.py
syringe_pumps/camera_control/camera.py
syringe_pumps/pump_control/pump_code_pack.py
syringe_pumps-0.1.3.dist-info/WHEEL
syringe_pumps-0.1.3.dist-info/METADATA
syringe_pumps-0.1.3.dist-info/RECORD
