Metadata-Version: 2.1
Name: syringe-pumps
Version: 0.1.3
Summary: Library for the control of syringe pumps
Author: Diana Arguijo
Requires-Python: >=3.8,<4.0
Classifier: Programming Language :: Python :: 3
Classifier: Programming Language :: Python :: 3.8
Classifier: Programming Language :: Python :: 3.9
